awt.py
cache_awt.py
conduits.py
html_util.py
awt-0.34.0.data/data/abif-catalog/abif_list.yml
awt-0.34.0.data/data/awt-static/abifwebtool.js
awt-0.34.0.data/data/awt-static/awt-electorama.svg
awt-0.34.0.data/data/awt-static/awtonly.svg
awt-0.34.0.data/data/awt-static/electodrop.svg
awt-0.34.0.data/data/awt-static/electostyle.css
awt-0.34.0.data/data/awt-static/favicon.ico
awt-0.34.0.data/data/awt-static/irvDisplay.js
awt-0.34.0.data/data/awt-static/main.js
awt-0.34.0.data/data/awt-static/popover.js
awt-0.34.0.data/data/awt-templates/abifbox-snippet.html
awt-0.34.0.data/data/awt-templates/all-snippet.html
awt-0.34.0.data/data/awt-templates/also-note-snippet.html
awt-0.34.0.data/data/awt-templates/approval-snippet.html
awt-0.34.0.data/data/awt-templates/base.html
awt-0.34.0.data/data/awt-templates/browse-index.html
awt-0.34.0.data/data/awt-templates/default-index.html
awt-0.34.0.data/data/awt-templates/election-list-snippet.html
awt-0.34.0.data/data/awt-templates/featured-snippet.html
awt-0.34.0.data/data/awt-templates/footer.snippet.html
awt-0.34.0.data/data/awt-templates/fptp-snippet.html
awt-0.34.0.data/data/awt-templates/homepage-index.html
awt-0.34.0.data/data/awt-templates/homepage-snippet.html
awt-0.34.0.data/data/awt-templates/id-index.html
awt-0.34.0.data/data/awt-templates/intro-snippet.html
awt-0.34.0.data/data/awt-templates/irv-snippet.html
awt-0.34.0.data/data/awt-templates/listitem-snippet.html
awt-0.34.0.data/data/awt-templates/methods-nav-snippit.html
awt-0.34.0.data/data/awt-templates/not-found.html
awt-0.34.0.data/data/awt-templates/notice-snippet.html
awt-0.34.0.data/data/awt-templates/pairwise-snippet.html
awt-0.34.0.data/data/awt-templates/pairwise-summary-only.html
awt-0.34.0.data/data/awt-templates/results-index.html
awt-0.34.0.data/data/awt-templates/scorestar-snippet.html
awt-0.34.0.data/data/awt-templates/star-snippet.html
awt-0.34.0.data/data/awt-templates/tag-browser-snippet.html
awt-0.34.0.data/data/awt-templates/tag-index.html
awt-0.34.0.dist-info/licenses/LICENSE
awt-0.34.0.dist-info/METADATA
awt-0.34.0.dist-info/WHEEL
awt-0.34.0.dist-info/entry_points.txt
awt-0.34.0.dist-info/top_level.txt
awt-0.34.0.dist-info/RECORD
