Metadata-Version: 2.4
Name: awt
Version: 0.34.0
Summary: awt == 'abif web tool'. It's a web interface for abiftool & abiflib.
Author-email: Rob Lanphier <robla@robla.net>
License: GPL-3.0
Classifier: Programming Language :: Python :: 3
Classifier: License :: OSI Approved :: GNU General Public License v3 or later (GPLv3+)
Classifier: Operating System :: OS Independent
Classifier: Intended Audience :: Science/Research
Classifier: Topic :: Sociology :: History
Requires-Python: >=3.8
License-File: LICENSE
Requires-Dist: abiftool>=0.34.0
Requires-Dist: dotenv
Requires-Dist: Flask
Requires-Dist: flask-caching
Requires-Dist: logging
Requires-Dist: PyYAML
Requires-Dist: setuptools
Requires-Dist: typing
Provides-Extra: linkpreview
Requires-Dist: cairosvg; extra == "linkpreview"
Dynamic: license-file
